sharepycrud/__init__.py
sharepycrud/auth.py
sharepycrud/client.py
sharepycrud/config.py
sharepycrud/utils.py
sharepycrud-0.1.1.dist-info/LICENSE
sharepycrud-0.1.1.dist-info/METADATA
sharepycrud-0.1.1.dist-info/WHEEL
sharepycrud-0.1.1.dist-info/top_level.txt
sharepycrud-0.1.1.dist-info/RECORD
